scrapy_seleniumbase_cdp/__init__.py
scrapy_seleniumbase_cdp/middleware_async.py
scrapy_seleniumbase_cdp/request.py
scrapy_seleniumbase_cdp-1.0.0.dist-info/METADATA
scrapy_seleniumbase_cdp-1.0.0.dist-info/WHEEL
scrapy_seleniumbase_cdp-1.0.0.dist-info/licenses/LICENSE
scrapy_seleniumbase_cdp-1.0.0.dist-info/RECORD
