Metadata-Version: 2.4
Name: scrapy-seleniumbase-cdp
Version: 1.0.0
Summary: Scrapy downloader middleware that uses SeleniumBase's pure CDP mode to make requests.
Project-URL: Homepage, https://github.com/nyg/scrapy-seleniumbase-cdp
Project-URL: Issues, https://github.com/nyg/scrapy-seleniumbase-cdp/issues
Author: nyg
License: MIT
License-File: LICENSE
Keywords: cdp,chrome-devtools-protocol,crawler,middleware,scrapy,seleniumbase,web-scraping
Classifier: Framework :: Scrapy
Classifier: Intended Audience :: Developers
Classifier: License :: OSI Approved :: MIT License
Classifier: Operating System :: OS Independent
Classifier: Programming Language :: Python :: 3
Classifier: Programming Language :: Python :: 3 :: Only
Requires-Python: >=3.10
Requires-Dist: mycdp>=1.0
Requires-Dist: scrapy>=2.0
Requires-Dist: seleniumbase>=4.0
